{
    "project_info": {
      "project_number": "1082132771534",
      "project_id": "musikahan-9adbe",
      "storage_bucket": "musikahan-9adbe.appspot.com"
    },
    "client": [
      {
        "client_info": {
          "mobilesdk_app_id": "1:1082132771534:android:b3a6f990dcbdfb3813969f",
          "android_client_info": {
            "package_name": "com.musikahan"
          }
        },
        "oauth_client": [],
        "api_key": [
          {
            "current_key": "AIzaSyDEnkDTjIS1KQSsxmSuhGYL-QpHvrOQR9A"
          }
        ],
        "services": {
          "appinvite_service": {
            "other_platform_oauth_client": []
          }
        }
      }
    ],
    "configuration_version": "1"
  }